<?xml version="1.0" encoding="utf-8"?>
<colorTheme id="6998" name="Emilia Dark" modified="2021-10-27T22:49:33.701Z" author="Alex Simons (Unthrottled)">
  <searchResultIndication color="#402a54" />
  <filteredSearchResultIndication color="#402a54" />
  <occurrenceIndication color="#442a55" underline="true" />
  <writeOccurrenceIndication color="#442a55" underline="true" />
  <findScope color="#402a54" />
  <deletionIndication color="#ff5555" />
  <sourceHoverBackground color="#442a55" />
  <singleLineComment color="#9277a7" italic="true" />
  <multiLineComment color="#9277a7" italic="true" />
  <commentTaskTag color="#F667FF" italic="true" underline="true" strikethrough="false" />
  <javadoc color="#9277a7" italic="true" />
  <javadocLink color="#BC60CB" italic="true" underline="true" strikethrough="false" />
  <javadocTag color="#a475ef" italic="true" />
  <javadocKeyword color="#a475ef" italic="true" />
  <class color="#FF9CD6" bold="false" underline="false" strikethrough="false" />
  <interface color="#a475ef" />
  <method color="#BC60CB" />
  <methodDeclaration color="#FF9CD6" />
  <bracket color="#DADADA" />
  <number color="#86dbfd" />
  <string color="#FDEFA2" />
  <operator color="#bca3aa" />
  <keyword color="#e049b0" bold="false" />
  <annotation color="#BC60CB" />
  <staticMethod color="#FF9CD6" />
  <localVariable color="#DADADA" />
  <localVariableDeclaration color="#DADADA" />
  <field color="#DADADA" bold="true" />
  <staticField color="#86dbfd" />
  <staticFinalField color="#86dbfd" italic="true" />
  <deprecatedMember color="#72737A" underline="false" strikethrough="true" />
  <enum color="#86dbfd" />
  <inheritedMethod color="#FF9CD6" />
  <abstractMethod color="#FF9CD6" />
  <parameterVariable color="#FDEFA2" />
  <typeArgument color="#a475ef" />
  <typeParameter color="#a475ef" />
  <constant color="#86dbfd" />
  <background color="#492d5a" />
  <currentLine color="#543466" />
  <foreground color="#DADADA" />
  <lineNumber color="#666879" />
  <selectionBackground color="#51256d" />
  <selectionForeground color="#d29eff" />
</colorTheme>