<?xml version="1.0" encoding="utf-8"?>
<colorTheme id="6997" name="Shigure" modified="2021-10-27T22:49:33.698Z" author="Alex Simons (Unthrottled)">
  <searchResultIndication color="#ddddff" />
  <filteredSearchResultIndication color="#ddddff" />
  <occurrenceIndication color="#e7d8f1" underline="true" />
  <writeOccurrenceIndication color="#e7d8f1" underline="true" />
  <findScope color="#ddddff" />
  <deletionIndication color="#FF0707" />
  <sourceHoverBackground color="#e7d8f1" />
  <singleLineComment color="#2E2E57" italic="true" />
  <multiLineComment color="#2E2E57" italic="true" />
  <commentTaskTag color="#a661b5" italic="true" underline="true" strikethrough="false" />
  <javadoc color="#2E2E57" italic="true" />
  <javadocLink color="#C209A9" italic="true" underline="true" strikethrough="false" />
  <javadocTag color="#5E037E" italic="true" />
  <javadocKeyword color="#5E037E" italic="true" />
  <class color="#7748B7" bold="false" underline="false" strikethrough="false" />
  <interface color="#5E037E" />
  <method color="#C209A9" />
  <methodDeclaration color="#7748B7" />
  <bracket color="#101010" />
  <number color="#005CC5" />
  <string color="#208D3B" />
  <operator color="#2811B9" />
  <keyword color="#410cb2" bold="false" />
  <annotation color="#C209A9" />
  <staticMethod color="#7748B7" />
  <localVariable color="#101010" />
  <localVariableDeclaration color="#101010" />
  <field color="#101010" bold="true" />
  <staticField color="#005CC5" />
  <staticFinalField color="#005CC5" italic="true" />
  <deprecatedMember color="#9291B0" underline="false" strikethrough="true" />
  <enum color="#005CC5" />
  <inheritedMethod color="#7748B7" />
  <abstractMethod color="#7748B7" />
  <parameterVariable color="#208D3B" />
  <typeArgument color="#5E037E" />
  <typeParameter color="#5E037E" />
  <constant color="#005CC5" />
  <background color="#e9e9ff" />
  <currentLine color="#d4d2ff" />
  <foreground color="#101010" />
  <lineNumber color="#38336b" />
  <selectionBackground color="#5756a2" />
  <selectionForeground color="#d3dcfd" />
</colorTheme>