<?xml version="1.0" encoding="utf-8"?>
<colorTheme id="7046" name="Monika Dark" modified="2023-01-22T19:40:08.259Z" author="Alex Simons (Unthrottled)">
  <searchResultIndication color="#252D19" />
  <filteredSearchResultIndication color="#252D19" />
  <occurrenceIndication color="#23271A" underline="true" />
  <writeOccurrenceIndication color="#23271A" underline="true" />
  <findScope color="#252D19" />
  <deletionIndication color="#ff5555" />
  <sourceHoverBackground color="#23271A" />
  <singleLineComment color="#647863" italic="true" />
  <multiLineComment color="#647863" italic="true" />
  <commentTaskTag color="#FFFA11" italic="true" underline="true" strikethrough="false" />
  <javadoc color="#647863" italic="true" />
  <javadocLink color="#60E769" italic="true" underline="true" strikethrough="false" />
  <javadocTag color="#ABFFAF" italic="true" />
  <javadocKeyword color="#ABFFAF" italic="true" />
  <class color="#FFEA82" bold="false" underline="false" strikethrough="false" />
  <interface color="#ABFFAF" />
  <method color="#60E769" />
  <methodDeclaration color="#FFEA82" />
  <bracket color="#bbbbbb" />
  <number color="#FF8FCA" />
  <string color="#94CFFF" />
  <operator color="#3eae5d" />
  <keyword color="#3eae5d" bold="false" />
  <annotation color="#60E769" />
  <staticMethod color="#FFEA82" />
  <localVariable color="#bbbbbb" />
  <localVariableDeclaration color="#bbbbbb" />
  <field color="#bbbbbb" bold="true" />
  <staticField color="#FF8FCA" />
  <staticFinalField color="#FF8FCA" italic="true" />
  <deprecatedMember color="#72737A" underline="false" strikethrough="true" />
  <enum color="#FF8FCA" />
  <inheritedMethod color="#FFEA82" />
  <abstractMethod color="#FFEA82" />
  <parameterVariable color="#94CFFF" />
  <typeArgument color="#ABFFAF" />
  <typeParameter color="#ABFFAF" />
  <constant color="#FF8FCA" />
  <background color="#1d2115" />
  <currentLine color="#24291a" />
  <foreground color="#bbbbbb" />
  <lineNumber color="#697966" />
  <selectionBackground color="#30432B" />
  <selectionForeground color="#ffffff" />
</colorTheme>